My_QR_COOLBOOY/__init__.py
My_QR_COOLBOOY/main.py
My_QR_COOLBOOY-1.1.1.dist-info/LICENSE
My_QR_COOLBOOY-1.1.1.dist-info/METADATA
My_QR_COOLBOOY-1.1.1.dist-info/WHEEL
My_QR_COOLBOOY-1.1.1.dist-info/entry_points.txt
My_QR_COOLBOOY-1.1.1.dist-info/top_level.txt
My_QR_COOLBOOY-1.1.1.dist-info/RECORD
