Metadata-Version: 2.1
Name: My-QR-COOLBOOY
Version: 1.1.1
Summary: A QR Code generator with customizable features
Author: coolbooy
Author-email: coolbooy@gmail.com
License: MIT
Classifier: Programming Language :: Python :: 3
Classifier: License :: OSI Approved :: MIT License
Classifier: Operating System :: OS Independent
Classifier: Intended Audience :: Developers
Requires-Python: >=3.6
License-File: LICENSE
Requires-Dist: qrcode
Requires-Dist: Pillow
